README.md
setup.py
pulse/__init__.py
pulse/batcher.py
pulse/formatters.py
pulse/handlers.py
pulse/metrics.py
pulse/version.py
pulse_logging.egg-info/PKG-INFO
pulse_logging.egg-info/SOURCES.txt
pulse_logging.egg-info/dependency_links.txt
pulse_logging.egg-info/requires.txt
pulse_logging.egg-info/top_level.txt